luminare/__init__.py
luminare/continuum.py
luminare/emulator.py
luminare/fourier.py
luminare/initial.py
luminare/nmf.py
luminare/scalers.py
luminare/utils.py
luminare-0.1.4.dist-info/METADATA
luminare-0.1.4.dist-info/WHEEL
luminare-0.1.4.dist-info/top_level.txt
luminare-0.1.4.dist-info/RECORD
